{
    "_": "VotesList",
    "count": 51,
    "votes": [
        {
            "_": "MessageUserVote",
            "user_id": 5764082456,
            "option": "b'1'",
            "date": "2023-05-06T17:38:18+00:00"
        },
        {
            "_": "MessageUserVote",
            "user_id": 596114319,
            "option": "b'1'",
            "date": "2023-01-15T19:17:10+00:00"
        },
        {
            "_": "MessageUserVote",
            "user_id": 5422863690,
            "option": "b'3'",
            "date": "2023-01-12T10:02:39+00:00"
        },
        {
            "_": "MessageUserVote",
            "user_id": 362481994,
            "option": "b'2'",
            "date": "2022-12-17T17:06:01+00:00"
        },
        {
            "_": "MessageUserVote",
            "user_id": 306225850,
            "option": "b'1'",
            "date": "2022-10-14T21:40:51+00:00"
        },
        {
            "_": "MessageUserVote",
            "user_id": 1772670536,
            "option": "b'3'",
            "date": "2022-09-06T22:01:50+00:00"
        },
        {
            "_": "MessageUserVote",
            "user_id": 271450383,
            "option": "b'0'",
            "date": "2022-09-06T22:01:29+00:00"
        },
        {
            "_": "MessageUserVote",
            "user_id": 313551595,
            "option": "b'2'",
            "date": "2022-08-29T13:42:41+00:00"
        },
        {
            "_": "MessageUserVote",
            "user_id": 307478806,
            "option": "b'2'",
            "date": "2022-08-28T12:07:28+00:00"
        },
        {
            "_": "MessageUserVote",
            "user_id": 397757944,
            "option": "b'3'",
            "date": "2022-08-28T10:08:44+00:00"
        },
        {
            "_": "MessageUserVote",
            "user_id": 1171150912,
            "option": "b'3'",
            "date": "2022-08-28T09:10:43+00:00"
        },
        {
            "_": "MessageUserVote",
            "user_id": 470932118,
            "option": "b'2'",
            "date": "2022-08-28T09:07:49+00:00"
        },
        {
            "_": "MessageUserVote",
            "user_id": 432584316,
            "option": "b'2'",
            "date": "2022-08-28T07:37:44+00:00"
        },
        {
            "_": "MessageUserVote",
            "user_id": 139373286,
            "option": "b'1'",
            "date": "2022-08-28T07:31:43+00:00"
        },
        {
            "_": "MessageUserVote",
            "user_id": 47917044,
            "option": "b'3'",
            "date": "2022-08-28T06:22:11+00:00"
        },
        {
            "_": "MessageUserVote",
            "user_id": 95355970,
            "option": "b'3'",
            "date": "2022-08-28T05:39:06+00:00"
        },
        {
            "_": "MessageUserVote",
            "user_id": 511275328,
            "option": "b'1'",
            "date": "2022-08-28T04:15:16+00:00"
        },
        {
            "_": "MessageUserVote",
            "user_id": 359999809,
            "option": "b'1'",
            "date": "2022-08-28T03:12:15+00:00"
        },
        {
            "_": "MessageUserVote",
            "user_id": 358653013,
            "option": "b'1'",
            "date": "2022-08-28T01:30:20+00:00"
        },
        {
            "_": "MessageUserVote",
            "user_id": 221459692,
            "option": "b'1'",
            "date": "2022-08-27T21:53:36+00:00"
        },
        {
            "_": "MessageUserVote",
            "user_id": 427777843,
            "option": "b'2'",
            "date": "2022-08-27T21:37:28+00:00"
        },
        {
            "_": "MessageUserVote",
            "user_id": 190920774,
            "option": "b'1'",
            "date": "2022-08-27T21:32:10+00:00"
        },
        {
            "_": "MessageUserVote",
            "user_id": 1222223435,
            "option": "b'1'",
            "date": "2022-08-27T21:28:07+00:00"
        },
        {
            "_": "MessageUserVote",
            "user_id": 1247107215,
            "option": "b'1'",
            "date": "2022-08-27T21:16:53+00:00"
        },
        {
            "_": "MessageUserVote",
            "user_id": 377820224,
            "option": "b'1'",
            "date": "2022-08-27T21:04:34+00:00"
        },
        {
            "_": "MessageUserVote",
            "user_id": 543423009,
            "option": "b'2'",
            "date": "2022-08-27T21:04:14+00:00"
        },
        {
            "_": "MessageUserVote",
            "user_id": 214236356,
            "option": "b'1'",
            "date": "2022-08-27T21:03:41+00:00"
        },
        {
            "_": "MessageUserVote",
            "user_id": 729127064,
            "option": "b'2'",
            "date": "2022-08-27T20:56:49+00:00"
        },
        {
            "_": "MessageUserVote",
            "user_id": 312815530,
            "option": "b'1'",
            "date": "2022-08-27T20:45:09+00:00"
        },
        {
            "_": "MessageUserVote",
            "user_id": 669828280,
            "option": "b'2'",
            "date": "2022-08-27T20:45:02+00:00"
        },
        {
            "_": "MessageUserVote",
            "user_id": 319855088,
            "option": "b'2'",
            "date": "2022-08-27T20:35:09+00:00"
        },
        {
            "_": "MessageUserVote",
            "user_id": 443431624,
            "option": "b'1'",
            "date": "2022-08-27T20:31:44+00:00"
        },
        {
            "_": "MessageUserVote",
            "user_id": 423183161,
            "option": "b'1'",
            "date": "2022-08-27T20:23:42+00:00"
        },
        {
            "_": "MessageUserVote",
            "user_id": 268957968,
            "option": "b'2'",
            "date": "2022-08-27T20:13:00+00:00"
        },
        {
            "_": "MessageUserVote",
            "user_id": 417780330,
            "option": "b'1'",
            "date": "2022-08-27T20:12:25+00:00"
        },
        {
            "_": "MessageUserVote",
            "user_id": 345477345,
            "option": "b'3'",
            "date": "2022-08-27T20:06:59+00:00"
        },
        {
            "_": "MessageUserVote",
            "user_id": 928898471,
            "option": "b'1'",
            "date": "2022-08-27T20:05:10+00:00"
        },
        {
            "_": "MessageUserVote",
            "user_id": 1030892455,
            "option": "b'3'",
            "date": "2022-08-27T19:59:05+00:00"
        },
        {
            "_": "MessageUserVote",
            "user_id": 739060114,
            "option": "b'1'",
            "date": "2022-08-27T19:53:33+00:00"
        },
        {
            "_": "MessageUserVote",
            "user_id": 523876778,
            "option": "b'1'",
            "date": "2022-08-27T19:52:23+00:00"
        },
        {
            "_": "MessageUserVote",
            "user_id": 1029299778,
            "option": "b'2'",
            "date": "2022-08-27T19:51:05+00:00"
        },
        {
            "_": "MessageUserVote",
            "user_id": 248863894,
            "option": "b'2'",
            "date": "2022-08-27T19:49:40+00:00"
        },
        {
            "_": "MessageUserVote",
            "user_id": 473603111,
            "option": "b'2'",
            "date": "2022-08-27T19:49:34+00:00"
        },
        {
            "_": "MessageUserVote",
            "user_id": 303627122,
            "option": "b'3'",
            "date": "2022-08-27T19:49:29+00:00"
        },
        {
            "_": "MessageUserVote",
            "user_id": 719375391,
            "option": "b'3'",
            "date": "2022-08-27T19:49:25+00:00"
        },
        {
            "_": "MessageUserVote",
            "user_id": 431784289,
            "option": "b'2'",
            "date": "2022-08-27T19:49:13+00:00"
        },
        {
            "_": "MessageUserVote",
            "user_id": 368671528,
            "option": "b'1'",
            "date": "2022-08-27T19:48:48+00:00"
        },
        {
            "_": "MessageUserVote",
            "user_id": 809083905,
            "option": "b'1'",
            "date": "2022-08-27T19:48:05+00:00"
        },
        {
            "_": "MessageUserVote",
            "user_id": 318272207,
            "option": "b'1'",
            "date": "2022-08-27T19:47:54+00:00"
        },
        {
            "_": "MessageUserVote",
            "user_id": 279128481,
            "option": "b'1'",
            "date": "2022-08-27T19:47:52+00:00"
        }
    ],
    "users": [
        {
            "_": "User",
            "id": 5764082456,
            "is_self": true,
            "contact": false,
            "mutual_contact": false,
            "deleted": false,
            "bot": false,
            "bot_chat_history": false,
            "bot_nochats": false,
            "verified": false,
            "restricted": false,
            "min": false,
            "bot_inline_geo": false,
            "support": false,
            "scam": false,
            "apply_min_photo": true,
            "fake": false,
            "bot_attach_menu": false,
            "premium": true,
            "attach_menu_enabled": false,
            "access_hash": 6343858599605164725,
            "first_name": "ВладимирЛатыпов",
            "last_name": "Подписочный",
            "username": "donRumataObserves",
            "phone": "79217617179",
            "photo": {
                "_": "UserProfilePhoto",
                "photo_id": 5251219139022929273,
                "dc_id": 2,
                "has_video": false,
                "personal": false,
                "stripped_thumb": "b'\\x01\\x08\\x08c\\x80\\xd2|\\xc7\\x8f\\xaf4QE \\xdc'"
            },
            "status": {
                "_": "UserStatusOnline",
                "expires": "2023-05-06T17:42:37+00:00"
            },
            "bot_info_version": null,
            "restriction_reason": [],
            "bot_inline_placeholder": null,
            "lang_code": null,
            "emoji_status": null,
            "usernames": []
        },
        {
            "_": "User",
            "id": 596114319,
            "is_self": false,
            "contact": false,
            "mutual_contact": false,
            "deleted": false,
            "bot": false,
            "bot_chat_history": false,
            "bot_nochats": false,
            "verified": false,
            "restricted": false,
            "min": false,
            "bot_inline_geo": false,
            "support": false,
            "scam": false,
            "apply_min_photo": true,
            "fake": false,
            "bot_attach_menu": false,
            "premium": false,
            "attach_menu_enabled": false,
            "access_hash": -122573637783794385,
            "first_name": "kseniia zolina",
            "last_name": null,
            "username": "toujours_s",
            "phone": null,
            "photo": {
                "_": "UserProfilePhoto",
                "photo_id": 2560291505238550461,
                "dc_id": 2,
                "has_video": false,
                "personal": false,
                "stripped_thumb": "b'\\x01\\x08\\x08h0\\xf9L\\x8c\\xc0\\xf00\\x08\\xe9E\\x14T\\x9b(&\\x7f'"
            },
            "status": {
                "_": "UserStatusOffline",
                "was_online": "2023-05-06T17:35:06+00:00"
            },
            "bot_info_version": null,
            "restriction_reason": [],
            "bot_inline_placeholder": null,
            "lang_code": null,
            "emoji_status": null,
            "usernames": []
        },
        {
            "_": "User",
            "id": 5422863690,
            "is_self": false,
            "contact": false,
            "mutual_contact": false,
            "deleted": false,
            "bot": false,
            "bot_chat_history": false,
            "bot_nochats": false,
            "verified": false,
            "restricted": false,
            "min": false,
            "bot_inline_geo": false,
            "support": false,
            "scam": false,
            "apply_min_photo": true,
            "fake": false,
            "bot_attach_menu": false,
            "premium": false,
            "attach_menu_enabled": false,
            "access_hash": -3628717427765867192,
            "first_name": "Даниил",
            "last_name": "Марценюк",
            "username": "engartion",
            "phone": null,
            "photo": null,
            "status": {
                "_": "UserStatusOffline",
                "was_online": "2023-05-06T17:36:43+00:00"
            },
            "bot_info_version": null,
            "restriction_reason": [],
            "bot_inline_placeholder": null,
            "lang_code": null,
            "emoji_status": null,
            "usernames": []
        },
        {
            "_": "User",
            "id": 362481994,
            "is_self": false,
            "contact": false,
            "mutual_contact": false,
            "deleted": false,
            "bot": false,
            "bot_chat_history": false,
            "bot_nochats": false,
            "verified": false,
            "restricted": false,
            "min": false,
            "bot_inline_geo": false,
            "support": false,
            "scam": false,
            "apply_min_photo": true,
            "fake": false,
            "bot_attach_menu": false,
            "premium": false,
            "attach_menu_enabled": false,
            "access_hash": 3984756532269153006,
            "first_name": "Artem",
            "last_name": "Zakharenko",
            "username": "fleex_x",
            "phone": null,
            "photo": {
                "_": "UserProfilePhoto",
                "photo_id": 1556848310075107258,
                "dc_id": 2,
                "has_video": false,
                "personal": false,
                "stripped_thumb": "b'\\x01\\x08\\x08z\\xdcH\\xd7EJ\\x8d\\xa7\\x8e\\xbd=\\xe8\\xa2\\x8ab\\xb1'"
            },
            "status": {
                "_": "UserStatusOffline",
                "was_online": "2023-01-29T16:18:00+00:00"
            },
            "bot_info_version": null,
            "restriction_reason": [],
            "bot_inline_placeholder": null,
            "lang_code": null,
            "emoji_status": null,
            "usernames": []
        },
        {
            "_": "User",
            "id": 306225850,
            "is_self": false,
            "contact": false,
            "mutual_contact": false,
            "deleted": false,
            "bot": false,
            "bot_chat_history": false,
            "bot_nochats": false,
            "verified": false,
            "restricted": false,
            "min": false,
            "bot_inline_geo": false,
            "support": false,
            "scam": false,
            "apply_min_photo": true,
            "fake": false,
            "bot_attach_menu": false,
            "premium": false,
            "attach_menu_enabled": false,
            "access_hash": 8565783743096961123,
            "first_name": "Diana",
            "last_name": null,
            "username": "roosidi",
            "phone": null,
            "photo": {
                "_": "UserProfilePhoto",
                "photo_id": 1315230011396041369,
                "dc_id": 2,
                "has_video": false,
                "personal": false,
                "stripped_thumb": "b'\\x01\\x08\\x08\\x82\\xea\\xe3x#\\x07\\xa0\\xcd\\x14QH\\xa7\\xa5\\x8f'"
            },
            "status": {
                "_": "UserStatusOffline",
                "was_online": "2023-05-06T15:40:48+00:00"
            },
            "bot_info_version": null,
            "restriction_reason": [],
            "bot_inline_placeholder": null,
            "lang_code": null,
            "emoji_status": null,
            "usernames": []
        },
        {
            "_": "User",
            "id": 1772670536,
            "is_self": false,
            "contact": false,
            "mutual_contact": false,
            "deleted": false,
            "bot": false,
            "bot_chat_history": false,
            "bot_nochats": false,
            "verified": false,
            "restricted": false,
            "min": false,
            "bot_inline_geo": false,
            "support": false,
            "scam": false,
            "apply_min_photo": true,
            "fake": false,
            "bot_attach_menu": false,
            "premium": false,
            "attach_menu_enabled": false,
            "access_hash": -4541453672096615781,
            "first_name": "Julia Kudinova",
            "last_name": null,
            "username": "xovotat",
            "phone": null,
            "photo": {
                "_": "UserProfilePhoto",
                "photo_id": 5287645916301477568,
                "dc_id": 2,
                "has_video": false,
                "personal": false,
                "stripped_thumb": "b'\\x01\\x08\\x08b\\\\fb\\xe4\\xfc\\x99\\xd9\\xb3\\xd2\\x8a(\\xac\\xa4Y'"
            },
            "status": {
                "_": "UserStatusOffline",
                "was_online": "2023-05-06T16:43:52+00:00"
            },
            "bot_info_version": null,
            "restriction_reason": [],
            "bot_inline_placeholder": null,
            "lang_code": null,
            "emoji_status": null,
            "usernames": []
        },
        {
            "_": "User",
            "id": 271450383,
            "is_self": false,
            "contact": false,
            "mutual_contact": false,
            "deleted": false,
            "bot": false,
            "bot_chat_history": false,
            "bot_nochats": false,
            "verified": false,
            "restricted": false,
            "min": false,
            "bot_inline_geo": false,
            "support": false,
            "scam": false,
            "apply_min_photo": true,
            "fake": false,
            "bot_attach_menu": false,
            "premium": false,
            "attach_menu_enabled": false,
            "access_hash": -3457630058023447297,
            "first_name": "Vasily",
            "last_name": "Lupuleac",
            "username": "Relayer1974",
            "phone": null,
            "photo": {
                "_": "UserProfilePhoto",
                "photo_id": 1165870517927913399,
                "dc_id": 2,
                "has_video": false,
                "personal": false,
                "stripped_thumb": "b'\\x01\\x08\\x08\\x8b\\xcc\\x89X\\xf23\\xbcc\\x8e\\x82\\x8a(\\xa9*\\xe7'"
            },
            "status": {
                "_": "UserStatusRecently"
            },
            "bot_info_version": null,
            "restriction_reason": [],
            "bot_inline_placeholder": null,
            "lang_code": null,
            "emoji_status": null,
            "usernames": []
        },
        {
            "_": "User",
            "id": 313551595,
            "is_self": false,
            "contact": false,
            "mutual_contact": false,
            "deleted": false,
            "bot": false,
            "bot_chat_history": false,
            "bot_nochats": false,
            "verified": false,
            "restricted": false,
            "min": false,
            "bot_inline_geo": false,
            "support": false,
            "scam": false,
            "apply_min_photo": true,
            "fake": false,
            "bot_attach_menu": false,
            "premium": true,
            "attach_menu_enabled": false,
            "access_hash": -2744525480239533343,
            "first_name": "Vyacheslav",
            "last_name": "Shabes",
            "username": "red_bullllllllllll",
            "phone": null,
            "photo": {
                "_": "UserProfilePhoto",
                "photo_id": 1346693846589876196,
                "dc_id": 2,
                "has_video": false,
                "personal": false,
                "stripped_thumb": "b'\\x01\\x08\\x08\\xce)\\x01\\x88\\x05??\\xaez\\xfe\\x14QE\\x03?'"
            },
            "status": {
                "_": "UserStatusOffline",
                "was_online": "2023-05-06T17:33:24+00:00"
            },
            "bot_info_version": null,
            "restriction_reason": [],
            "bot_inline_placeholder": null,
            "lang_code": null,
            "emoji_status": {
                "_": "EmojiStatus",
                "document_id": 5373098778439982772
            },
            "usernames": []
        },
        {
            "_": "User",
            "id": 307478806,
            "is_self": false,
            "contact": false,
            "mutual_contact": false,
            "deleted": false,
            "bot": false,
            "bot_chat_history": false,
            "bot_nochats": false,
            "verified": false,
            "restricted": false,
            "min": false,
            "bot_inline_geo": false,
            "support": false,
            "scam": false,
            "apply_min_photo": true,
            "fake": false,
            "bot_attach_menu": false,
            "premium": true,
            "attach_menu_enabled": false,
            "access_hash": 3765180558672394069,
            "first_name": "Таня",
            "last_name": "Гордеева",
            "username": "sarnatk",
            "phone": null,
            "photo": {
                "_": "UserProfilePhoto",
                "photo_id": 1320611416439367688,
                "dc_id": 2,
                "has_video": false,
                "personal": false,
                "stripped_thumb": "b'\\x01\\x08\\x08\\x94\\xdc\\xaa\\xdc*\\x93\\xc1m\\xa3\\x07\\xf9\\xfe4QE\\x00\\x7f'"
            },
            "status": {
                "_": "UserStatusOffline",
                "was_online": "2023-05-06T17:34:39+00:00"
            },
            "bot_info_version": null,
            "restriction_reason": [],
            "bot_inline_placeholder": null,
            "lang_code": null,
            "emoji_status": {
                "_": "EmojiStatus",
                "document_id": 5201928375890879480
            },
            "usernames": []
        },
        {
            "_": "User",
            "id": 397757944,
            "is_self": false,
            "contact": false,
            "mutual_contact": false,
            "deleted": false,
            "bot": false,
            "bot_chat_history": false,
            "bot_nochats": false,
            "verified": false,
            "restricted": false,
            "min": false,
            "bot_inline_geo": false,
            "support": false,
            "scam": false,
            "apply_min_photo": true,
            "fake": false,
            "bot_attach_menu": false,
            "premium": false,
            "attach_menu_enabled": false,
            "access_hash": -6660185538449076232,
            "first_name": "Сергей",
            "last_name": "Дымашевский",
            "username": "Dymashevskij_Sergey",
            "phone": null,
            "photo": {
                "_": "UserProfilePhoto",
                "photo_id": 1708357361660438460,
                "dc_id": 2,
                "has_video": false,
                "personal": false,
                "stripped_thumb": "b'\\x01\\x08\\x08\\x11L\\xa7+\\xb7o\\xff\\x00^\\x8a(\\xac\\x94\\x9a\\xd9\\x96\\xd2?'"
            },
            "status": {
                "_": "UserStatusRecently"
            },
            "bot_info_version": null,
            "restriction_reason": [],
            "bot_inline_placeholder": null,
            "lang_code": null,
            "emoji_status": null,
            "usernames": []
        },
        {
            "_": "User",
            "id": 1171150912,
            "is_self": false,
            "contact": false,
            "mutual_contact": false,
            "deleted": false,
            "bot": false,
            "bot_chat_history": false,
            "bot_nochats": false,
            "verified": false,
            "restricted": false,
            "min": false,
            "bot_inline_geo": false,
            "support": false,
            "scam": false,
            "apply_min_photo": true,
            "fake": false,
            "bot_attach_menu": false,
            "premium": true,
            "attach_menu_enabled": false,
            "access_hash": -3639597897273758289,
            "first_name": "валера",
            "last_name": "мацкевич",
            "username": "blonded04",
            "phone": null,
            "photo": {
                "_": "UserProfilePhoto",
                "photo_id": 5240342465058294018,
                "dc_id": 2,
                "has_video": true,
                "personal": false,
                "stripped_thumb": "b'\\x01\\x08\\x08\\x97p\\xdb\\xd3\\x9f\\xad\\x14Q]*)\\x1as\\xb3'"
            },
            "status": {
                "_": "UserStatusRecently"
            },
            "bot_info_version": null,
            "restriction_reason": [],
            "bot_inline_placeholder": null,
            "lang_code": null,
            "emoji_status": {
                "_": "EmojiStatus",
                "document_id": 5372923973271034075
            },
            "usernames": []
        },
        {
            "_": "User",
            "id": 470932118,
            "is_self": false,
            "contact": false,
            "mutual_contact": false,
            "deleted": false,
            "bot": false,
            "bot_chat_history": false,
            "bot_nochats": false,
            "verified": false,
            "restricted": false,
            "min": false,
            "bot_inline_geo": false,
            "support": false,
            "scam": false,
            "apply_min_photo": true,
            "fake": false,
            "bot_attach_menu": false,
            "premium": true,
            "attach_menu_enabled": false,
            "access_hash": 4900027767464931118,
            "first_name": "Egor",
            "last_name": "Lebedev",
            "username": "lebedev_egor",
            "phone": null,
            "photo": {
                "_": "UserProfilePhoto",
                "photo_id": 2022638045902252095,
                "dc_id": 2,
                "has_video": true,
                "personal": false,
                "stripped_thumb": "b'\\x01\\x08\\x08\\x8br\\xc9\\xbeV!Kv# QE\\x15B?'"
            },
            "status": {
                "_": "UserStatusOffline",
                "was_online": "2023-05-06T06:22:29+00:00"
            },
            "bot_info_version": null,
            "restriction_reason": [],
            "bot_inline_placeholder": null,
            "lang_code": null,
            "emoji_status": {
                "_": "EmojiStatus",
                "document_id": 5275998295250968947
            },
            "usernames": []
        },
        {
            "_": "User",
            "id": 432584316,
            "is_self": false,
            "contact": false,
            "mutual_contact": false,
            "deleted": false,
            "bot": false,
            "bot_chat_history": false,
            "bot_nochats": false,
            "verified": false,
            "restricted": false,
            "min": false,
            "bot_inline_geo": false,
            "support": false,
            "scam": false,
            "apply_min_photo": true,
            "fake": false,
            "bot_attach_menu": false,
            "premium": false,
            "attach_menu_enabled": false,
            "access_hash": 5748693502891088781,
            "first_name": "Nikita",
            "last_name": "Khramov",
            "username": "mr_khram",
            "phone": null,
            "photo": {
                "_": "UserProfilePhoto",
                "photo_id": 1857935490438768559,
                "dc_id": 2,
                "has_video": false,
                "personal": false,
                "stripped_thumb": "b'\\x01\\x08\\x08\\x83\\xed(\\xf7\\x19\\xf9\\x95~\\xee\\x0f\\xad\\x14QWrl\\x7f'"
            },
            "status": {
                "_": "UserStatusOffline",
                "was_online": "2023-05-06T16:28:44+00:00"
            },
            "bot_info_version": null,
            "restriction_reason": [],
            "bot_inline_placeholder": null,
            "lang_code": null,
            "emoji_status": null,
            "usernames": []
        },
        {
            "_": "User",
            "id": 139373286,
            "is_self": false,
            "contact": false,
            "mutual_contact": false,
            "deleted": false,
            "bot": false,
            "bot_chat_history": false,
            "bot_nochats": false,
            "verified": false,
            "restricted": false,
            "min": false,
            "bot_inline_geo": false,
            "support": false,
            "scam": false,
            "apply_min_photo": true,
            "fake": false,
            "bot_attach_menu": false,
            "premium": false,
            "attach_menu_enabled": false,
            "access_hash": 5814342398457782625,
            "first_name": "Anna",
            "last_name": "Polupanova",
            "username": "lamniskataa",
            "phone": null,
            "photo": {
                "_": "UserProfilePhoto",
                "photo_id": 598603705762293705,
                "dc_id": 2,
                "has_video": true,
                "personal": false,
                "stripped_thumb": "b'\\x01\\x08\\x08X\\x1b$`\\x9f\\x9f\\xe6\\x18\\xef\\xcfj(\\xa2\\xa7b\\xee\\x7f'"
            },
            "status": {
                "_": "UserStatusOnline",
                "expires": "2023-05-06T17:41:50+00:00"
            },
            "bot_info_version": null,
            "restriction_reason": [],
            "bot_inline_placeholder": null,
            "lang_code": null,
            "emoji_status": null,
            "usernames": []
        },
        {
            "_": "User",
            "id": 47917044,
            "is_self": false,
            "contact": false,
            "mutual_contact": false,
            "deleted": false,
            "bot": false,
            "bot_chat_history": false,
            "bot_nochats": false,
            "verified": false,
            "restricted": false,
            "min": false,
            "bot_inline_geo": false,
            "support": false,
            "scam": false,
            "apply_min_photo": true,
            "fake": false,
            "bot_attach_menu": false,
            "premium": false,
            "attach_menu_enabled": false,
            "access_hash": 485924674201206928,
            "first_name": "Anton",
            "last_name": "Yermilov",
            "username": "antonyermilov",
            "phone": null,
            "photo": {
                "_": "UserProfilePhoto",
                "photo_id": 205802137357233297,
                "dc_id": 2,
                "has_video": false,
                "personal": false,
                "stripped_thumb": "b'\\x01\\x08\\x08tw\\x08\\xf3H\\xc5\\x8a\\x97\\x1c\\x0fZ(\\xa2\\x93v\\x03'"
            },
            "status": {
                "_": "UserStatusRecently"
            },
            "bot_info_version": null,
            "restriction_reason": [],
            "bot_inline_placeholder": null,
            "lang_code": null,
            "emoji_status": null,
            "usernames": []
        },
        {
            "_": "User",
            "id": 95355970,
            "is_self": false,
            "contact": false,
            "mutual_contact": false,
            "deleted": false,
            "bot": false,
            "bot_chat_history": false,
            "bot_nochats": false,
            "verified": false,
            "restricted": false,
            "min": false,
            "bot_inline_geo": false,
            "support": false,
            "scam": false,
            "apply_min_photo": true,
            "fake": false,
            "bot_attach_menu": false,
            "premium": true,
            "attach_menu_enabled": false,
            "access_hash": -2962861628677994063,
            "first_name": "Vasily",
            "last_name": "Alferov",
            "username": "vasilyalferov",
            "phone": null,
            "photo": {
                "_": "UserProfilePhoto",
                "photo_id": 409550773084596176,
                "dc_id": 2,
                "has_video": false,
                "personal": false,
                "stripped_thumb": "b'\\x01\\x08\\x08Ui\\x8c\\x88\\xc7s\\x80s\\x81\\xdb\\x8a(\\xa2\\xa9\\t\\x9f'"
            },
            "status": {
                "_": "UserStatusRecently"
            },
            "bot_info_version": null,
            "restriction_reason": [],
            "bot_inline_placeholder": null,
            "lang_code": null,
            "emoji_status": null,
            "usernames": []
        },
        {
            "_": "User",
            "id": 511275328,
            "is_self": false,
            "contact": false,
            "mutual_contact": false,
            "deleted": false,
            "bot": false,
            "bot_chat_history": false,
            "bot_nochats": false,
            "verified": false,
            "restricted": false,
            "min": false,
            "bot_inline_geo": false,
            "support": false,
            "scam": false,
            "apply_min_photo": true,
            "fake": false,
            "bot_attach_menu": false,
            "premium": false,
            "attach_menu_enabled": false,
            "access_hash": 9215099157180118625,
            "first_name": "Regina",
            "last_name": null,
            "username": "schneiderdies",
            "phone": null,
            "photo": {
                "_": "UserProfilePhoto",
                "photo_id": 2195910813467912123,
                "dc_id": 2,
                "has_video": false,
                "personal": false,
                "stripped_thumb": "b'\\x01\\x08\\x08l\\xb1\\xb9\\x88\\xb3E\\xfb\\xc2\\xddE\\x14QQr\\xf9O'"
            },
            "status": {
                "_": "UserStatusRecently"
            },
            "bot_info_version": null,
            "restriction_reason": [],
            "bot_inline_placeholder": null,
            "lang_code": null,
            "emoji_status": null,
            "usernames": []
        },
        {
            "_": "User",
            "id": 359999809,
            "is_self": false,
            "contact": false,
            "mutual_contact": false,
            "deleted": false,
            "bot": false,
            "bot_chat_history": false,
            "bot_nochats": false,
            "verified": false,
            "restricted": false,
            "min": false,
            "bot_inline_geo": false,
            "support": false,
            "scam": false,
            "apply_min_photo": true,
            "fake": false,
            "bot_attach_menu": false,
            "premium": false,
            "attach_menu_enabled": false,
            "access_hash": 1734699414977578774,
            "first_name": "German",
            "last_name": "Tarabonda",
            "username": "geh_4",
            "phone": null,
            "photo": {
                "_": "UserProfilePhoto",
                "photo_id": 1546187406677485548,
                "dc_id": 2,
                "has_video": false,
                "personal": false,
                "stripped_thumb": "b'\\x01\\x08\\x08\\xab-\\xe8\\x96\\x12\\x850{{s\\xd6\\x8a(\\xa0\\xab\\x1f'"
            },
            "status": {
                "_": "UserStatusRecently"
            },
            "bot_info_version": null,
            "restriction_reason": [],
            "bot_inline_placeholder": null,
            "lang_code": null,
            "emoji_status": null,
            "usernames": []
        },
        {
            "_": "User",
            "id": 358653013,
            "is_self": false,
            "contact": false,
            "mutual_contact": false,
            "deleted": false,
            "bot": false,
            "bot_chat_history": false,
            "bot_nochats": false,
            "verified": false,
            "restricted": false,
            "min": false,
            "bot_inline_geo": false,
            "support": false,
            "scam": false,
            "apply_min_photo": true,
            "fake": false,
            "bot_attach_menu": false,
            "premium": false,
            "attach_menu_enabled": false,
            "access_hash": 2955298001165875811,
            "first_name": "Ilya",
            "last_name": "Brovarnik",
            "username": "ilybro",
            "phone": null,
            "photo": {
                "_": "UserProfilePhoto",
                "photo_id": 1540402961903101900,
                "dc_id": 2,
                "has_video": false,
                "personal": false,
                "stripped_thumb": "b'\\x01\\x08\\x08\\x8evQ\\x17\\x19\\r\\x9c\\xf4\\xa2\\x8a*\\x12\\xd0\\xd2Ri\\x9f'"
            },
            "status": {
                "_": "UserStatusOffline",
                "was_online": "2023-05-06T17:24:40+00:00"
            },
            "bot_info_version": null,
            "restriction_reason": [],
            "bot_inline_placeholder": null,
            "lang_code": null,
            "emoji_status": null,
            "usernames": []
        },
        {
            "_": "User",
            "id": 221459692,
            "is_self": false,
            "contact": false,
            "mutual_contact": false,
            "deleted": false,
            "bot": false,
            "bot_chat_history": false,
            "bot_nochats": false,
            "verified": false,
            "restricted": false,
            "min": false,
            "bot_inline_geo": false,
            "support": false,
            "scam": false,
            "apply_min_photo": true,
            "fake": false,
            "bot_attach_menu": false,
            "premium": false,
            "attach_menu_enabled": false,
            "access_hash": -4847403814431553310,
            "first_name": "Viacheslav",
            "last_name": "Vorobev",
            "username": "slava3141",
            "phone": null,
            "photo": {
                "_": "UserProfilePhoto",
                "photo_id": 951162134978471859,
                "dc_id": 2,
                "has_video": false,
                "personal": false,
                "stripped_thumb": "b'\\x01\\x08\\x08X\\x99\\xe4~@\\xda\\x7fJ(\\xa2\\x9c[\\t$\\x7f'"
            },
            "status": {
                "_": "UserStatusOffline",
                "was_online": "2023-05-06T17:34:49+00:00"
            },
            "bot_info_version": null,
            "restriction_reason": [],
            "bot_inline_placeholder": null,
            "lang_code": null,
            "emoji_status": null,
            "usernames": []
        },
        {
            "_": "User",
            "id": 427777843,
            "is_self": false,
            "contact": false,
            "mutual_contact": false,
            "deleted": false,
            "bot": false,
            "bot_chat_history": false,
            "bot_nochats": false,
            "verified": false,
            "restricted": false,
            "min": false,
            "bot_inline_geo": false,
            "support": false,
            "scam": false,
            "apply_min_photo": true,
            "fake": false,
            "bot_attach_menu": false,
            "premium": false,
            "attach_menu_enabled": false,
            "access_hash": 2515972847225053227,
            "first_name": "Dan",
            "last_name": "Nesterov",
            "username": "DanNesterov",
            "phone": null,
            "photo": null,
            "status": {
                "_": "UserStatusRecently"
            },
            "bot_info_version": null,
            "restriction_reason": [],
            "bot_inline_placeholder": null,
            "lang_code": null,
            "emoji_status": null,
            "usernames": []
        },
        {
            "_": "User",
            "id": 190920774,
            "is_self": false,
            "contact": false,
            "mutual_contact": false,
            "deleted": false,
            "bot": false,
            "bot_chat_history": false,
            "bot_nochats": false,
            "verified": false,
            "restricted": false,
            "min": false,
            "bot_inline_geo": false,
            "support": false,
            "scam": false,
            "apply_min_photo": true,
            "fake": false,
            "bot_attach_menu": false,
            "premium": false,
            "attach_menu_enabled": false,
            "access_hash": -7435239069577495726,
            "first_name": "Alexander",
            "last_name": "Kovrigin",
            "username": "waleko",
            "phone": null,
            "photo": {
                "_": "UserProfilePhoto",
                "photo_id": 819998480913246152,
                "dc_id": 2,
                "has_video": false,
                "personal": false,
                "stripped_thumb": "b'\\x01\\x08\\x08|W(.\\x0eY\\xb1\\xd3\\xda\\x8a(\\xa9\\xb9\\xb2\\x82h'"
            },
            "status": {
                "_": "UserStatusRecently"
            },
            "bot_info_version": null,
            "restriction_reason": [],
            "bot_inline_placeholder": null,
            "lang_code": null,
            "emoji_status": null,
            "usernames": []
        },
        {
            "_": "User",
            "id": 1222223435,
            "is_self": false,
            "contact": false,
            "mutual_contact": false,
            "deleted": false,
            "bot": false,
            "bot_chat_history": false,
            "bot_nochats": false,
            "verified": false,
            "restricted": false,
            "min": false,
            "bot_inline_geo": false,
            "support": false,
            "scam": false,
            "apply_min_photo": true,
            "fake": false,
            "bot_attach_menu": false,
            "premium": false,
            "attach_menu_enabled": false,
            "access_hash": 475465490902171061,
            "first_name": "Екатерина",
            "last_name": "Инкина",
            "username": "redogruna",
            "phone": null,
            "photo": {
                "_": "UserProfilePhoto",
                "photo_id": 5377339900187232366,
                "dc_id": 2,
                "has_video": false,
                "personal": false,
                "stripped_thumb": "b'\\x01\\x08\\x08p\\xbbP\\xe3y8\\xefE\\x14Vi\\x96\\xd1'"
            },
            "status": {
                "_": "UserStatusOnline",
                "expires": "2023-05-06T17:42:49+00:00"
            },
            "bot_info_version": null,
            "restriction_reason": [],
            "bot_inline_placeholder": null,
            "lang_code": null,
            "emoji_status": null,
            "usernames": []
        },
        {
            "_": "User",
            "id": 1247107215,
            "is_self": false,
            "contact": false,
            "mutual_contact": false,
            "deleted": false,
            "bot": false,
            "bot_chat_history": false,
            "bot_nochats": false,
            "verified": false,
            "restricted": false,
            "min": false,
            "bot_inline_geo": false,
            "support": false,
            "scam": false,
            "apply_min_photo": true,
            "fake": false,
            "bot_attach_menu": false,
            "premium": false,
            "attach_menu_enabled": false,
            "access_hash": -6287700505086346898,
            "first_name": "温馨",
            "last_name": null,
            "username": "shinebright21",
            "phone": null,
            "photo": {
                "_": "UserProfilePhoto",
                "photo_id": 5235891826672651780,
                "dc_id": 2,
                "has_video": false,
                "personal": false,
                "stripped_thumb": "b'\\x01\\x08\\x08\\xcdy\\x11\\xa1\\xdb\\xces\\x9a(\\xa2\\x81\\x9f'"
            },
            "status": {
                "_": "UserStatusRecently"
            },
            "bot_info_version": null,
            "restriction_reason": [],
            "bot_inline_placeholder": null,
            "lang_code": null,
            "emoji_status": null,
            "usernames": []
        },
        {
            "_": "User",
            "id": 377820224,
            "is_self": false,
            "contact": false,
            "mutual_contact": false,
            "deleted": false,
            "bot": false,
            "bot_chat_history": false,
            "bot_nochats": false,
            "verified": false,
            "restricted": false,
            "min": false,
            "bot_inline_geo": false,
            "support": false,
            "scam": false,
            "apply_min_photo": true,
            "fake": false,
            "bot_attach_menu": false,
            "premium": false,
            "attach_menu_enabled": false,
            "access_hash": 1090803832367097839,
            "first_name": "Iurii",
            "last_name": "Zaitsev",
            "username": "hello_zoka",
            "phone": null,
            "photo": {
                "_": "UserProfilePhoto",
                "photo_id": 1622725506303633328,
                "dc_id": 2,
                "has_video": false,
                "personal": false,
                "stripped_thumb": "b'\\x01\\x08\\x08X\\xa4\\xff\\x00H\\x12\\x10A<u\\xe0\\x03\\xda\\x8a(\\xac\\x8e\\x89E&\\x7f'"
            },
            "status": {
                "_": "UserStatusRecently"
            },
            "bot_info_version": null,
            "restriction_reason": [],
            "bot_inline_placeholder": null,
            "lang_code": null,
            "emoji_status": null,
            "usernames": []
        },
        {
            "_": "User",
            "id": 543423009,
            "is_self": false,
            "contact": false,
            "mutual_contact": false,
            "deleted": false,
            "bot": false,
            "bot_chat_history": false,
            "bot_nochats": false,
            "verified": false,
            "restricted": false,
            "min": false,
            "bot_inline_geo": false,
            "support": false,
            "scam": false,
            "apply_min_photo": true,
            "fake": false,
            "bot_attach_menu": false,
            "premium": false,
            "attach_menu_enabled": false,
            "access_hash": -5658945042297311157,
            "first_name": "kmmba",
            "last_name": null,
            "username": "keklimamba",
            "phone": null,
            "photo": {
                "_": "UserProfilePhoto",
                "photo_id": 2333984052005152688,
                "dc_id": 2,
                "has_video": false,
                "personal": false,
                "stripped_thumb": "b'\\x01\\x08\\x08d\\xd3\\xca\\xbfx\\xfc\\xc5~\\x94QE$6\\x7f'"
            },
            "status": {
                "_": "UserStatusOffline",
                "was_online": "2023-05-06T12:25:51+00:00"
            },
            "bot_info_version": null,
            "restriction_reason": [],
            "bot_inline_placeholder": null,
            "lang_code": null,
            "emoji_status": null,
            "usernames": []
        },
        {
            "_": "User",
            "id": 214236356,
            "is_self": false,
            "contact": false,
            "mutual_contact": false,
            "deleted": false,
            "bot": false,
            "bot_chat_history": false,
            "bot_nochats": false,
            "verified": false,
            "restricted": false,
            "min": false,
            "bot_inline_geo": false,
            "support": false,
            "scam": false,
            "apply_min_photo": true,
            "fake": false,
            "bot_attach_menu": false,
            "premium": false,
            "attach_menu_enabled": false,
            "access_hash": -6860460341335694212,
            "first_name": "Georgii",
            "last_name": "Kuksa",
            "username": "kuksag",
            "phone": null,
            "photo": {
                "_": "UserProfilePhoto",
                "photo_id": 920138143090452423,
                "dc_id": 2,
                "has_video": false,
                "personal": false,
                "stripped_thumb": "b'\\x01\\x08\\x08\\x87\\r\\x83\\xf2\\x9d\\xa0zQE\\x15\\x9d\\xcag'"
            },
            "status": {
                "_": "UserStatusRecently"
            },
            "bot_info_version": null,
            "restriction_reason": [],
            "bot_inline_placeholder": null,
            "lang_code": null,
            "emoji_status": null,
            "usernames": []
        },
        {
            "_": "User",
            "id": 729127064,
            "is_self": false,
            "contact": false,
            "mutual_contact": false,
            "deleted": false,
            "bot": false,
            "bot_chat_history": false,
            "bot_nochats": false,
            "verified": false,
            "restricted": false,
            "min": false,
            "bot_inline_geo": false,
            "support": false,
            "scam": false,
            "apply_min_photo": true,
            "fake": false,
            "bot_attach_menu": false,
            "premium": false,
            "attach_menu_enabled": false,
            "access_hash": -2902261472671471073,
            "first_name": "Григорий",
            "last_name": "Абросимов",
            "username": "rpuwazz",
            "phone": "79058264974",
            "photo": {
                "_": "UserProfilePhoto",
                "photo_id": 3131576894964737990,
                "dc_id": 2,
                "has_video": false,
                "personal": false,
                "stripped_thumb": "b\"\\x01\\x08\\x08b\\xe7'?\\x85\\x14QX\\xd9\\x1cm\\xdc\""
            },
            "status": {
                "_": "UserStatusOnline",
                "expires": "2023-05-06T17:43:05+00:00"
            },
            "bot_info_version": null,
            "restriction_reason": [],
            "bot_inline_placeholder": null,
            "lang_code": null,
            "emoji_status": null,
            "usernames": []
        },
        {
            "_": "User",
            "id": 312815530,
            "is_self": false,
            "contact": false,
            "mutual_contact": false,
            "deleted": false,
            "bot": false,
            "bot_chat_history": false,
            "bot_nochats": false,
            "verified": false,
            "restricted": false,
            "min": false,
            "bot_inline_geo": false,
            "support": false,
            "scam": false,
            "apply_min_photo": true,
            "fake": false,
            "bot_attach_menu": false,
            "premium": false,
            "attach_menu_enabled": false,
            "access_hash": 794286567768007956,
            "first_name": "Андрей",
            "last_name": "Поштаренко",
            "username": "QWERTYUIOPWAJAVAVDLDOBEB2HDUXKD9",
            "phone": "79094017251",
            "photo": {
                "_": "UserProfilePhoto",
                "photo_id": 1343532471487145922,
                "dc_id": 2,
                "has_video": false,
                "personal": false,
                "stripped_thumb": "b'\\x01\\x08\\x08\\xab\\xe5\\x17\\x8bj\\x86/\\xbb\\x8c}(\\xa2\\x8ai\\t\\x9f'"
            },
            "status": {
                "_": "UserStatusOffline",
                "was_online": "2023-05-06T17:37:36+00:00"
            },
            "bot_info_version": null,
            "restriction_reason": [],
            "bot_inline_placeholder": null,
            "lang_code": null,
            "emoji_status": null,
            "usernames": []
        },
        {
            "_": "User",
            "id": 669828280,
            "is_self": false,
            "contact": false,
            "mutual_contact": false,
            "deleted": false,
            "bot": false,
            "bot_chat_history": false,
            "bot_nochats": false,
            "verified": false,
            "restricted": false,
            "min": false,
            "bot_inline_geo": false,
            "support": false,
            "scam": false,
            "apply_min_photo": true,
            "fake": false,
            "bot_attach_menu": false,
            "premium": false,
            "attach_menu_enabled": false,
            "access_hash": 4819019149050774898,
            "first_name": "ᚩeðor",
            "last_name": "Gromóv",
            "username": "Sidim_Theoden",
            "phone": null,
            "photo": {
                "_": "UserProfilePhoto",
                "photo_id": 2876890556992170033,
                "dc_id": 2,
                "has_video": false,
                "personal": false,
                "stripped_thumb": "b'\\x01\\x08\\x08\\xa0\\x1dc`\\x19F\\xd3\\xfa\\x1a(\\xa2\\x80?'"
            },
            "status": {
                "_": "UserStatusRecently"
            },
            "bot_info_version": null,
            "restriction_reason": [],
            "bot_inline_placeholder": null,
            "lang_code": null,
            "emoji_status": null,
            "usernames": []
        },
        {
            "_": "User",
            "id": 319855088,
            "is_self": false,
            "contact": false,
            "mutual_contact": false,
            "deleted": false,
            "bot": false,
            "bot_chat_history": false,
            "bot_nochats": false,
            "verified": false,
            "restricted": false,
            "min": false,
            "bot_inline_geo": false,
            "support": false,
            "scam": false,
            "apply_min_photo": true,
            "fake": false,
            "bot_attach_menu": false,
            "premium": false,
            "attach_menu_enabled": false,
            "access_hash": 2175031076914224242,
            "first_name": "Aigerim",
            "last_name": "Assylkhanova",
            "username": "aigerimass",
            "phone": null,
            "photo": {
                "_": "UserProfilePhoto",
                "photo_id": 1373767142875441279,
                "dc_id": 2,
                "has_video": false,
                "personal": false,
                "stripped_thumb": "b'\\x01\\x08\\x08\\xa9\\x1c\\x91\\x9br\\x81@$\\xe3q\\xe9\\x8cQE\\x15%\\x9f'"
            },
            "status": {
                "_": "UserStatusOffline",
                "was_online": "2023-05-06T17:37:20+00:00"
            },
            "bot_info_version": null,
            "restriction_reason": [],
            "bot_inline_placeholder": null,
            "lang_code": null,
            "emoji_status": null,
            "usernames": []
        },
        {
            "_": "User",
            "id": 443431624,
            "is_self": false,
            "contact": false,
            "mutual_contact": false,
            "deleted": false,
            "bot": false,
            "bot_chat_history": false,
            "bot_nochats": false,
            "verified": false,
            "restricted": false,
            "min": false,
            "bot_inline_geo": false,
            "support": false,
            "scam": false,
            "apply_min_photo": true,
            "fake": false,
            "bot_attach_menu": false,
            "premium": false,
            "attach_menu_enabled": false,
            "access_hash": -3641339710169155515,
            "first_name": "Miron",
            "last_name": "Ganin",
            "username": "morph228322",
            "phone": null,
            "photo": {
                "_": "UserProfilePhoto",
                "photo_id": 1904524323548407735,
                "dc_id": 2,
                "has_video": false,
                "personal": false,
                "stripped_thumb": "b'\\x01\\x08\\x08\\x16x\\xd5\\x90\\xf9\\xb8\\xc1\\xc1^\\xd4QE!\\x9f'"
            },
            "status": {
                "_": "UserStatusRecently"
            },
            "bot_info_version": null,
            "restriction_reason": [],
            "bot_inline_placeholder": null,
            "lang_code": null,
            "emoji_status": null,
            "usernames": []
        },
        {
            "_": "User",
            "id": 423183161,
            "is_self": false,
            "contact": false,
            "mutual_contact": false,
            "deleted": false,
            "bot": false,
            "bot_chat_history": false,
            "bot_nochats": false,
            "verified": false,
            "restricted": false,
            "min": false,
            "bot_inline_geo": false,
            "support": false,
            "scam": false,
            "apply_min_photo": true,
            "fake": false,
            "bot_attach_menu": false,
            "premium": false,
            "attach_menu_enabled": false,
            "access_hash": -2949507756826558850,
            "first_name": "Егор Шереметов",
            "last_name": null,
            "username": "egor_sheremetov",
            "phone": null,
            "photo": {
                "_": "UserProfilePhoto",
                "photo_id": 1817557837169141681,
                "dc_id": 2,
                "has_video": false,
                "personal": false,
                "stripped_thumb": "b'\\x01\\x08\\x08\\x98\\\\!\\xba\\xc8\\x97\\x8c\\xed\\xeb\\xc5\\x14QRQ'"
            },
            "status": {
                "_": "UserStatusRecently"
            },
            "bot_info_version": null,
            "restriction_reason": [],
            "bot_inline_placeholder": null,
            "lang_code": null,
            "emoji_status": null,
            "usernames": []
        },
        {
            "_": "User",
            "id": 268957968,
            "is_self": false,
            "contact": false,
            "mutual_contact": false,
            "deleted": false,
            "bot": false,
            "bot_chat_history": false,
            "bot_nochats": false,
            "verified": false,
            "restricted": false,
            "min": false,
            "bot_inline_geo": false,
            "support": false,
            "scam": false,
            "apply_min_photo": true,
            "fake": false,
            "bot_attach_menu": false,
            "premium": false,
            "attach_menu_enabled": false,
            "access_hash": 5173778532944356758,
            "first_name": "Aleksandr",
            "last_name": null,
            "username": null,
            "phone": null,
            "photo": null,
            "status": {
                "_": "UserStatusRecently"
            },
            "bot_info_version": null,
            "restriction_reason": [],
            "bot_inline_placeholder": null,
            "lang_code": null,
            "emoji_status": null,
            "usernames": []
        },
        {
            "_": "User",
            "id": 417780330,
            "is_self": false,
            "contact": false,
            "mutual_contact": false,
            "deleted": false,
            "bot": false,
            "bot_chat_history": false,
            "bot_nochats": false,
            "verified": false,
            "restricted": false,
            "min": false,
            "bot_inline_geo": false,
            "support": false,
            "scam": false,
            "apply_min_photo": true,
            "fake": false,
            "bot_attach_menu": false,
            "premium": false,
            "attach_menu_enabled": false,
            "access_hash": -8211549330202273892,
            "first_name": "Миляушá",
            "last_name": "Сабирова",
            "username": "milyaushas",
            "phone": null,
            "photo": {
                "_": "UserProfilePhoto",
                "photo_id": 1794352854718326897,
                "dc_id": 2,
                "has_video": false,
                "personal": false,
                "stripped_thumb": "b'\\x01\\x08\\x08`+\\xe4\\x95d\\xf9\\xfad\\x0e\\x94QEG34\\xe5G'"
            },
            "status": {
                "_": "UserStatusRecently"
            },
            "bot_info_version": null,
            "restriction_reason": [],
            "bot_inline_placeholder": null,
            "lang_code": null,
            "emoji_status": null,
            "usernames": []
        },
        {
            "_": "User",
            "id": 345477345,
            "is_self": false,
            "contact": false,
            "mutual_contact": false,
            "deleted": false,
            "bot": false,
            "bot_chat_history": false,
            "bot_nochats": false,
            "verified": false,
            "restricted": false,
            "min": false,
            "bot_inline_geo": false,
            "support": false,
            "scam": false,
            "apply_min_photo": true,
            "fake": false,
            "bot_attach_menu": false,
            "premium": true,
            "attach_menu_enabled": false,
            "access_hash": 1260011681137573205,
            "first_name": "Kirill",
            "last_name": "Karnaukhov",
            "username": "kkarnauk",
            "phone": null,
            "photo": {
                "_": "UserProfilePhoto",
                "photo_id": 1483813898740148323,
                "dc_id": 2,
                "has_video": false,
                "personal": false,
                "stripped_thumb": "b'\\x01\\x08\\x08py\\x0b\\x8c\\xa2\\x81\\xfcX\\xed\\xf4\\xa2\\x8a+\"\\xcf'"
            },
            "status": {
                "_": "UserStatusOffline",
                "was_online": "2023-05-06T17:24:43+00:00"
            },
            "bot_info_version": null,
            "restriction_reason": [],
            "bot_inline_placeholder": null,
            "lang_code": null,
            "emoji_status": {
                "_": "EmojiStatus",
                "document_id": 5400258833064927568
            },
            "usernames": []
        },
        {
            "_": "User",
            "id": 928898471,
            "is_self": false,
            "contact": false,
            "mutual_contact": false,
            "deleted": false,
            "bot": false,
            "bot_chat_history": false,
            "bot_nochats": false,
            "verified": false,
            "restricted": false,
            "min": false,
            "bot_inline_geo": false,
            "support": false,
            "scam": false,
            "apply_min_photo": true,
            "fake": false,
            "bot_attach_menu": false,
            "premium": false,
            "attach_menu_enabled": false,
            "access_hash": -7695342283201793147,
            "first_name": "Veronika",
            "last_name": "Sirotkina",
            "username": "ozzush",
            "phone": null,
            "photo": {
                "_": "UserProfilePhoto",
                "photo_id": 3989588554705643449,
                "dc_id": 2,
                "has_video": false,
                "personal": false,
                "stripped_thumb": "b'\\x01\\x08\\x08G\\xbe\\xfd\\xf7\\xcb\\x92\\xbd1\\x8a(\\xa2\\xa5\\x94\\x7f'"
            },
            "status": {
                "_": "UserStatusOffline",
                "was_online": "2023-05-06T17:15:58+00:00"
            },
            "bot_info_version": null,
            "restriction_reason": [],
            "bot_inline_placeholder": null,
            "lang_code": null,
            "emoji_status": null,
            "usernames": []
        },
        {
            "_": "User",
            "id": 1030892455,
            "is_self": false,
            "contact": false,
            "mutual_contact": false,
            "deleted": false,
            "bot": false,
            "bot_chat_history": false,
            "bot_nochats": false,
            "verified": false,
            "restricted": false,
            "min": false,
            "bot_inline_geo": false,
            "support": false,
            "scam": false,
            "apply_min_photo": true,
            "fake": false,
            "bot_attach_menu": false,
            "premium": true,
            "attach_menu_enabled": false,
            "access_hash": 5910967661161819792,
            "first_name": "Stepan",
            "last_name": "Konstantinov",
            "username": "constantor",
            "phone": null,
            "photo": {
                "_": "UserProfilePhoto",
                "photo_id": 4427649380374390729,
                "dc_id": 2,
                "has_video": false,
                "personal": false,
                "stripped_thumb": "b'\\x01\\x08\\x08f\\x08\\x8f*\\x03\\x92\\xbc\\x9fJ(\\xa2\\x9a\\x03'"
            },
            "status": {
                "_": "UserStatusOffline",
                "was_online": "2023-05-06T17:21:10+00:00"
            },
            "bot_info_version": null,
            "restriction_reason": [],
            "bot_inline_placeholder": null,
            "lang_code": null,
            "emoji_status": {
                "_": "EmojiStatus",
                "document_id": 5213305508034783384
            },
            "usernames": []
        },
        {
            "_": "User",
            "id": 739060114,
            "is_self": false,
            "contact": false,
            "mutual_contact": false,
            "deleted": false,
            "bot": false,
            "bot_chat_history": false,
            "bot_nochats": false,
            "verified": false,
            "restricted": false,
            "min": false,
            "bot_inline_geo": false,
            "support": false,
            "scam": false,
            "apply_min_photo": true,
            "fake": false,
            "bot_attach_menu": false,
            "premium": false,
            "attach_menu_enabled": false,
            "access_hash": -1693644631733864864,
            "first_name": "Daria",
            "last_name": "Shutina",
            "username": "deshyt",
            "phone": null,
            "photo": {
                "_": "UserProfilePhoto",
                "photo_id": 3174239019864270835,
                "dc_id": 2,
                "has_video": false,
                "personal": false,
                "stripped_thumb": "b'\\x01\\x08\\x08\\xac\\x04\\x9eR\\xc6A\\xe0\\x93\\xd7\\x8a(\\xa2\\x90\\xcf'"
            },
            "status": {
                "_": "UserStatusOffline",
                "was_online": "2023-05-06T16:33:56+00:00"
            },
            "bot_info_version": null,
            "restriction_reason": [],
            "bot_inline_placeholder": null,
            "lang_code": null,
            "emoji_status": null,
            "usernames": []
        },
        {
            "_": "User",
            "id": 523876778,
            "is_self": false,
            "contact": false,
            "mutual_contact": false,
            "deleted": false,
            "bot": false,
            "bot_chat_history": false,
            "bot_nochats": false,
            "verified": false,
            "restricted": false,
            "min": false,
            "bot_inline_geo": false,
            "support": false,
            "scam": false,
            "apply_min_photo": true,
            "fake": false,
            "bot_attach_menu": false,
            "premium": false,
            "attach_menu_enabled": false,
            "access_hash": -4015240269243268657,
            "first_name": "Vladislav",
            "last_name": "Naumkin",
            "username": "N4V1S",
            "phone": null,
            "photo": {
                "_": "UserProfilePhoto",
                "photo_id": 2250033629100091312,
                "dc_id": 2,
                "has_video": false,
                "personal": false,
                "stripped_thumb": "b'\\x01\\x08\\x08\\x81U\"?!\\xe3\\xebE\\x14U\\x08'"
            },
            "status": {
                "_": "UserStatusRecently"
            },
            "bot_info_version": null,
            "restriction_reason": [],
            "bot_inline_placeholder": null,
            "lang_code": null,
            "emoji_status": null,
            "usernames": []
        },
        {
            "_": "User",
            "id": 1029299778,
            "is_self": false,
            "contact": false,
            "mutual_contact": false,
            "deleted": false,
            "bot": false,
            "bot_chat_history": false,
            "bot_nochats": false,
            "verified": false,
            "restricted": false,
            "min": false,
            "bot_inline_geo": false,
            "support": false,
            "scam": false,
            "apply_min_photo": true,
            "fake": false,
            "bot_attach_menu": false,
            "premium": false,
            "attach_menu_enabled": false,
            "access_hash": 8981501339357173535,
            "first_name": "Дарья",
            "last_name": null,
            "username": "be_my_fire",
            "phone": null,
            "photo": {
                "_": "UserProfilePhoto",
                "photo_id": 4420808884746299316,
                "dc_id": 2,
                "has_video": false,
                "personal": false,
                "stripped_thumb": "b'\\x01\\x08\\x08\\x8d\\xe7\\x0b\\x93\\x9f\\xba\\xdbH\\x07\\xaeh\\xa2\\x8a\\x95\\x04[\\x91'"
            },
            "status": {
                "_": "UserStatusRecently"
            },
            "bot_info_version": null,
            "restriction_reason": [],
            "bot_inline_placeholder": null,
            "lang_code": null,
            "emoji_status": null,
            "usernames": []
        },
        {
            "_": "User",
            "id": 248863894,
            "is_self": false,
            "contact": false,
            "mutual_contact": false,
            "deleted": false,
            "bot": false,
            "bot_chat_history": false,
            "bot_nochats": false,
            "verified": false,
            "restricted": false,
            "min": false,
            "bot_inline_geo": false,
            "support": false,
            "scam": false,
            "apply_min_photo": true,
            "fake": false,
            "bot_attach_menu": false,
            "premium": false,
            "attach_menu_enabled": false,
            "access_hash": -212405772471230724,
            "first_name": "Elizaveta",
            "last_name": "Zhemchuzhina",
            "username": "lizazhemchuzhina",
            "phone": null,
            "photo": {
                "_": "UserProfilePhoto",
                "photo_id": 1068862286341449886,
                "dc_id": 2,
                "has_video": false,
                "personal": false,
                "stripped_thumb": "b'\\x01\\x08\\x08\\xb8Y\\x84\\xb8\\x08H\\xdd\\xd7\\x14QE\\x00\\x7f'"
            },
            "status": {
                "_": "UserStatusRecently"
            },
            "bot_info_version": null,
            "restriction_reason": [],
            "bot_inline_placeholder": null,
            "lang_code": null,
            "emoji_status": null,
            "usernames": []
        },
        {
            "_": "User",
            "id": 473603111,
            "is_self": false,
            "contact": false,
            "mutual_contact": false,
            "deleted": false,
            "bot": false,
            "bot_chat_history": false,
            "bot_nochats": false,
            "verified": false,
            "restricted": false,
            "min": false,
            "bot_inline_geo": false,
            "support": false,
            "scam": false,
            "apply_min_photo": true,
            "fake": false,
            "bot_attach_menu": false,
            "premium": true,
            "attach_menu_enabled": false,
            "access_hash": -7235801852354430097,
            "first_name": "Никита",
            "last_name": "Денисов",
            "username": "NVDenisov",
            "phone": null,
            "photo": {
                "_": "UserProfilePhoto",
                "photo_id": 2034109873485096940,
                "dc_id": 2,
                "has_video": false,
                "personal": false,
                "stripped_thumb": "b'\\x01\\x08\\x08\\xaa-f\\x03\\xca\\xf2\\xc8\\x93>\\xbcb\\x8a(\\xab\\x11'"
            },
            "status": {
                "_": "UserStatusOnline",
                "expires": "2023-05-06T17:42:54+00:00"
            },
            "bot_info_version": null,
            "restriction_reason": [],
            "bot_inline_placeholder": null,
            "lang_code": null,
            "emoji_status": {
                "_": "EmojiStatus",
                "document_id": 5445096582238181549
            },
            "usernames": []
        },
        {
            "_": "User",
            "id": 303627122,
            "is_self": false,
            "contact": false,
            "mutual_contact": false,
            "deleted": false,
            "bot": false,
            "bot_chat_history": false,
            "bot_nochats": false,
            "verified": false,
            "restricted": false,
            "min": false,
            "bot_inline_geo": false,
            "support": false,
            "scam": false,
            "apply_min_photo": true,
            "fake": false,
            "bot_attach_menu": false,
            "premium": false,
            "attach_menu_enabled": false,
            "access_hash": 3433177975347150619,
            "first_name": "Ramazan",
            "last_name": "Dzhekshembaev",
            "username": "RMZS0711",
            "phone": "79588010925",
            "photo": {
                "_": "UserProfilePhoto",
                "photo_id": 1304068559624841273,
                "dc_id": 2,
                "has_video": true,
                "personal": false,
                "stripped_thumb": "b'\\x01\\x08\\x08\\xcd\\x91\\xd7\\xcc\\xc6\\xdc`\\xf3E\\x14R\\xb0\\xcf'"
            },
            "status": {
                "_": "UserStatusOffline",
                "was_online": "2023-05-06T17:23:34+00:00"
            },
            "bot_info_version": null,
            "restriction_reason": [],
            "bot_inline_placeholder": null,
            "lang_code": null,
            "emoji_status": null,
            "usernames": []
        },
        {
            "_": "User",
            "id": 719375391,
            "is_self": false,
            "contact": false,
            "mutual_contact": false,
            "deleted": false,
            "bot": false,
            "bot_chat_history": false,
            "bot_nochats": false,
            "verified": false,
            "restricted": false,
            "min": false,
            "bot_inline_geo": false,
            "support": false,
            "scam": false,
            "apply_min_photo": true,
            "fake": false,
            "bot_attach_menu": false,
            "premium": true,
            "attach_menu_enabled": false,
            "access_hash": 8481855007040744496,
            "first_name": "Andrey",
            "last_name": "Chalenko",
            "username": "chasgbc",
            "phone": "79994956290",
            "photo": {
                "_": "UserProfilePhoto",
                "photo_id": 3089693778348451860,
                "dc_id": 2,
                "has_video": false,
                "personal": false,
                "stripped_thumb": "b'\\x01\\x08\\x08\\xa8B|\\xa0\\x03\\xd7\\x04\\x8e\\xf4QE ?'"
            },
            "status": {
                "_": "UserStatusRecently"
            },
            "bot_info_version": null,
            "restriction_reason": [],
            "bot_inline_placeholder": null,
            "lang_code": null,
            "emoji_status": {
                "_": "EmojiStatus",
                "document_id": 5454086459889821382
            },
            "usernames": []
        },
        {
            "_": "User",
            "id": 431784289,
            "is_self": false,
            "contact": false,
            "mutual_contact": false,
            "deleted": false,
            "bot": false,
            "bot_chat_history": false,
            "bot_nochats": false,
            "verified": false,
            "restricted": false,
            "min": false,
            "bot_inline_geo": false,
            "support": false,
            "scam": false,
            "apply_min_photo": true,
            "fake": false,
            "bot_attach_menu": false,
            "premium": false,
            "attach_menu_enabled": false,
            "access_hash": 1879856341512191510,
            "first_name": "Федор",
            "last_name": "Бондарь",
            "username": "fedyamathboi",
            "phone": null,
            "photo": {
                "_": "UserProfilePhoto",
                "photo_id": 1854499400637851589,
                "dc_id": 2,
                "has_video": false,
                "personal": false,
                "stripped_thumb": "b'\\x01\\x08\\x08{\\\\\\x13u\\xdb\\x18\\xdb\\xf8u\\xcd\\x14Q@\\x1f'"
            },
            "status": {
                "_": "UserStatusRecently"
            },
            "bot_info_version": null,
            "restriction_reason": [],
            "bot_inline_placeholder": null,
            "lang_code": null,
            "emoji_status": null,
            "usernames": []
        },
        {
            "_": "User",
            "id": 368671528,
            "is_self": false,
            "contact": true,
            "mutual_contact": false,
            "deleted": false,
            "bot": false,
            "bot_chat_history": false,
            "bot_nochats": false,
            "verified": false,
            "restricted": false,
            "min": false,
            "bot_inline_geo": false,
            "support": false,
            "scam": false,
            "apply_min_photo": true,
            "fake": false,
            "bot_attach_menu": false,
            "premium": false,
            "attach_menu_enabled": false,
            "access_hash": 642036437865120895,
            "first_name": "Марк",
            "last_name": "Ипатов",
            "username": "c0deEater",
            "phone": "79523695546",
            "photo": {
                "_": "UserProfilePhoto",
                "photo_id": 1583432156182587378,
                "dc_id": 2,
                "has_video": false,
                "personal": false,
                "stripped_thumb": "b'\\x01\\x08\\x08\\x8c1\\x11\\xec\\x08\\x01\\xeb\\xbb4QEM\\x8b?'"
            },
            "status": {
                "_": "UserStatusOffline",
                "was_online": "2023-05-06T17:30:35+00:00"
            },
            "bot_info_version": null,
            "restriction_reason": [],
            "bot_inline_placeholder": null,
            "lang_code": null,
            "emoji_status": null,
            "usernames": []
        },
        {
            "_": "User",
            "id": 809083905,
            "is_self": false,
            "contact": false,
            "mutual_contact": false,
            "deleted": false,
            "bot": false,
            "bot_chat_history": false,
            "bot_nochats": false,
            "verified": false,
            "restricted": false,
            "min": false,
            "bot_inline_geo": false,
            "support": false,
            "scam": false,
            "apply_min_photo": true,
            "fake": false,
            "bot_attach_menu": false,
            "premium": false,
            "attach_menu_enabled": false,
            "access_hash": -4606926021563862488,
            "first_name": "Серж",
            "last_name": "Шиманский",
            "username": "EKCnEPT_nO_T9IHKAM",
            "phone": null,
            "photo": {
                "_": "UserProfilePhoto",
                "photo_id": 3474988912151209916,
                "dc_id": 2,
                "has_video": false,
                "personal": false,
                "stripped_thumb": "b'\\x01\\x08\\x08\\x9d\\x06od\\xe5w\\x86\\x1f1\\x1cg\\x14QE\\x01s'"
            },
            "status": {
                "_": "UserStatusRecently"
            },
            "bot_info_version": null,
            "restriction_reason": [],
            "bot_inline_placeholder": null,
            "lang_code": null,
            "emoji_status": null,
            "usernames": []
        },
        {
            "_": "User",
            "id": 318272207,
            "is_self": false,
            "contact": false,
            "mutual_contact": false,
            "deleted": false,
            "bot": false,
            "bot_chat_history": false,
            "bot_nochats": false,
            "verified": false,
            "restricted": false,
            "min": false,
            "bot_inline_geo": false,
            "support": false,
            "scam": false,
            "apply_min_photo": true,
            "fake": false,
            "bot_attach_menu": false,
            "premium": false,
            "attach_menu_enabled": false,
            "access_hash": -320511596757518171,
            "first_name": "Alexander",
            "last_name": "Fedorov",
            "username": "Alehard",
            "phone": null,
            "photo": {
                "_": "UserProfilePhoto",
                "photo_id": 1366968720746981305,
                "dc_id": 2,
                "has_video": false,
                "personal": false,
                "stripped_thumb": "b'\\x01\\x08\\x08\\xafi/\\x95\\xc31RO\\xe1E\\x14U8\\xab\\x82g'"
            },
            "status": {
                "_": "UserStatusOffline",
                "was_online": "2023-05-06T17:24:59+00:00"
            },
            "bot_info_version": null,
            "restriction_reason": [],
            "bot_inline_placeholder": null,
            "lang_code": null,
            "emoji_status": null,
            "usernames": []
        },
        {
            "_": "User",
            "id": 279128481,
            "is_self": false,
            "contact": false,
            "mutual_contact": false,
            "deleted": false,
            "bot": false,
            "bot_chat_history": false,
            "bot_nochats": false,
            "verified": false,
            "restricted": false,
            "min": false,
            "bot_inline_geo": false,
            "support": false,
            "scam": false,
            "apply_min_photo": true,
            "fake": false,
            "bot_attach_menu": false,
            "premium": true,
            "attach_menu_enabled": false,
            "access_hash": -1980947156675591141,
            "first_name": "Sergei",
            "last_name": "Kharitontcev-Beglov",
            "username": "doktorkrab",
            "phone": null,
            "photo": {
                "_": "UserProfilePhoto",
                "photo_id": 1198847697733396424,
                "dc_id": 2,
                "has_video": false,
                "personal": false,
                "stripped_thumb": "b'\\x01\\x08\\x08\\x82ER\\xaa\\xeb1\\xc9=O\\\\\\xd1E\\x14\\x8a\\xb1'"
            },
            "status": {
                "_": "UserStatusRecently"
            },
            "bot_info_version": null,
            "restriction_reason": [],
            "bot_inline_placeholder": null,
            "lang_code": null,
            "emoji_status": {
                "_": "EmojiStatus",
                "document_id": 5463297085975567150
            },
            "usernames": []
        }
    ],
    "next_offset": "1661629672_279128481"
}